MANIFEST.in
README.md
ez_setup.py
setup.py
metaphor/__init__.py
metaphor/version_test.py
metaphor/test_monal/__init__.py
metaphor/test_monal/__main__.py
metaphor/test_monal/main.py
metaphor/test_monal/monal_tests.py
metaphor/test_monal/test_data_manager.py
metaphor/test_monal/test_libManager.py
metaphor/test_monal/test_linalg.py
metaphor/test_monal/test_monal_module.py
metaphor/test_monal/test_monaltoolbox.py
metaphor/test_monal/test_property.py
metaphor/test_monal/test_toolbox.py
metaphor/test_monal/test_utils.py
metaphor/test_monal/testFiles/B321_19d_JLPloix.xlsx
metaphor/test_monal/testFiles/BJMA244_Test25_5SM.xls
metaphor/test_monal/testFiles/BJMA244_Test25_5SM.xlsx
metaphor/test_monal/testFiles/BJMA244_Test25_5SM_data.csv
metaphor/test_monal/testFiles/BJMA244_Test25_5SM_data.txt
metaphor/test_monal/testFiles/BJMA244_Test25_5SM_test.csv
metaphor/test_monal/testFiles/BJMA244_Test25_5SM_test.txt
metaphor/test_monal/testFiles/BJMA244_Test25_SM.xlsx
metaphor/test_monal/testFiles/BJMA244_Test25_SM_10S_5N.nnx
metaphor/test_monal/testFiles/Base10.csv
metaphor/test_monal/testFiles/Base321E_chem.xlsx
metaphor/test_monal/testFiles/BoxLucas.csv
metaphor/test_monal/testFiles/GM_B13C81Acetophenones_50T_0I_150E_10S_SEED1947_5N.nnx
metaphor/test_monal/testFiles/L_153.csv
metaphor/test_monal/testFiles/L_153.txt
metaphor/test_monal/testFiles/L_153.xlsx
metaphor/test_monal/testFiles/L_153_10S_5N.nnx
metaphor/test_monal/testFiles/L_153_Inverse.csv
metaphor/test_monal/testFiles/LogKd-baseA109.txt
metaphor/test_monal/testFiles/NN_L_153_150T_5I_150E_10S_SEED3307226117_5N.nnx
metaphor/test_monal/testFiles/PoidsASCII10.txt
metaphor/test_monal/testFiles/PoidsNML10.nml
metaphor/test_monal/testFiles/WW10.npy
metaphor/test_monal/testFiles/demo_.txt
metaphor/test_monal/testFiles/kirby2.csv
metaphor/test_monal/testFiles/libbase109_chi1_grds5_5n.so
metaphor/test_monal/testFiles/libbase321e_chem_chi1_grds1_1n_ce4.so
metaphor/test_monal/testFiles/libbasea109_chi01n.so
metaphor_test.egg-info/PKG-INFO
metaphor_test.egg-info/SOURCES.txt
metaphor_test.egg-info/dependency_links.txt
metaphor_test.egg-info/entry_points.txt
metaphor_test.egg-info/not-zip-safe
metaphor_test.egg-info/requires.txt
metaphor_test.egg-info/top_level.txt